Workbook

Sheet objects
A1: Name | B1: Generation Method | C1: Description | D1: Purpose (Attribution) | E1: *Purpose (Analytics) | F1: Granularity | G1: Field Count | H1: generate? | I1: generation_order | J1: Generate_Rows | K1: existing consumption project | L1: bps_roi_rw | M1: extend the views/objects | N1: Phase | O1: Order
A2: Interactions | B2: Source System | C2: Tracked activities by individuals that show they are engaging with an Asset. | D2: This Justifies that the marketing activity was engaged with by the individual and so supports the implication that thier buying decision was influenced by the result. Greater strength of interaction with marketing activity can be used for increased attribution of outcome to that activity. | E2: This may be used for more targeted and channel specific assets engagement reporting. | F2: Each row links one person to one activity. There may be multiple interactions for a person to an Activity | G2: =COUNTIF(Attributes!A:A,objects!A8) -> 17 | H2: y | I2: 17 | J2: 500000 | N2: MVP-1 | O2: 1
A3: Marketing Activity | B3: Source System | C3: Outbound, proactive, targeted distribution of marketing assets (e.g., emails, calls, direct mail). Or Organic, content-driven strategies that attract and engage audiences on their own terms (e.g., social posts, billboards, website content). | D3: This Identifies the actions that BT Carries out and is ultimately the most granular element of Marketing activity that BT can optimise. | E3: Again this is a baseline for the marketing activity that has been carried out by BT. | F3: Each Row represents the Sending of a single assets to a single contact point which may be an individual or company. This is based on the experiance of the reciepient, So technical retries due to failure wouldn’t result in multiple rows, But if the User recieved two duplicate messages at the same time this would be 2 seperate rows. This covers everyone who was selected in the audience to receive the communication, Including the Control Cell audience. OR Each Row represents a BT action to any number of people. Each action should have a Time or a timeframe where it would be consistantly showing the same asset. Given the audience is Unknown one row here might have multiple engagements from Multiple Individuals or Companies. | G3: =COUNTIF(Attributes!A:A,objects!A7) -> 0 | H3: y | I3: 15 | J3: 10000 | N3: MVP-1 | O3: 2
A4: Orders | B4: Source System | C4: Point in Time revenue generating events related to a specific company and product. | D4: This is an outcome to be attributed to influence activities. | E4: Used to show the attributed outcomes | F4: Each Row should be a single product, sold at a specific point in time, to a specific company. Order of multiple units could be grouped to a single row. Mutiple different products sold at the same time to the same company as part of a single purchase event should still be different rows. | G4: =COUNTIF(Attributes!A:A,objects!A13) -> 4 | H4: y | I4: 9 | J4: 70000 | N4: MVP-1 | O4: 3
A5: Person | B5: Source System | C5: This contains all information related to an individual who is a customer or prospect | D5: Used as part of the linking chain for activities through to outcomes. Person attributes may contribute to external factors for weighting of attribution. | E5: May be used for non attribution analytics looking at specific person activity. Useful for specific attribution investigation and validation. | F5: To be decided, Might be outside the scope of this project to resolve person identities. Suggested initially maintain the grain of the source systems person objects. So a Row represents one marketo person record,… | G5: =COUNTIF(Attributes!A:A,objects!A10) -> 4 | H5: y | I5: 7 | J5: 50000 | N5: MVP-1 | O5: 4
A6: Company | B6: Source System | C6: This represents a company entity at potentially multiple grains. | D6: Used as part of the linking chain for activities through to outcomes. People link to a company, Outcomes link to a company, Companies link to other companies through thier hierachy. Company attributes may contribute to external factors for weighting of attribution. | E6: May be used for non attribution analytics looking at specific company activity. Useful for specific attribution investigation and validation. | F6: Each Row represents on company object at a specific BT grain, I.E. CUG or Billing Account,… These objects would have self hierarchicle relationships that links for example billing accounts to CUGs. So there would be a row for each billing account then a seperate row for each CUG,… The MDM project may result in a more standardised object being available. At which point it may be that all activity and Outcomes can be standardised to a specific grain. | G6: =COUNTIF(Attributes!A:A,objects!A11) -> 34 | H6: y | I6: 6 | J6: 30000 | N6: MVP-1 | O6: 4
A7: Person Company Role | B7: Source System | C7: Represents the relationship a person has with a company. I.E. decision maker, influences. Enables the concept of a person have relationships with multiple companies. | D7: Used as part of the linking of activity to outcome. Role used for attribution wieghting and filtering. | E7: Useful for other non attribution analytical views. | F7: Each row represents a the role a person has with a company. The same person may be linked to the same company multiple times with different roles. this would be multiple rows. | G7: =COUNTIF(Attributes!A:A,objects!A12) -> 5 | H7: N | I7: 8 | J7: Dependant | O7: 4
A8: Attribution Linking Table | B8: Derived | C8: The cross reference table between the Marketing Activity and Outcome Tables. | D8: This contains the raw relationships that could be attributed. | E8: Not useful for Other Analytical purposes. | F8: Each Row represents the relationship between an outcome and an activity for a Given model. | G8: =COUNTIF(Attributes!A:A,objects!A9) -> 8 | H8: Y | I8: 18 | J8: Dependant | N8: MVP-1 | O8: 5
A9: Products | B9: Source System | C9: Describes the BT Product Catelogue at different levels and contains the hierachy of products | D9: Enables linking of both marketing activity and outcomes to the same products for relevance matching. | E9: Used for comparing and filtering across all levels. | F9: Each Row represents a product or group or family, All levels of heirachy are contained. | G9: =COUNTIF(Attributes!A:A,objects!A19) -> 0 | H9: Y | I9: 0 | N9: MVP-1 | O9: 6
A10: Attribution Model Output Table | B10: Data Science Team | C10: Percentages that a model has assigned as the impact of a marketing activity to an outcome. | D10: This is the Main output for the attribution modelling | E10: Core to all attribution metrics | F10: Each Row represents a single marketing activity linked to a single outcome for a particular model. There may be multiple models that have assigned different attribution levels for the same marketing activity to the same outcome element. Within a single model there would neven be multiple entries for the same marketing activity and outcome element interaction. Not every marketing activity will be linked to event outcome element. | G10: =COUNTIF(Attributes!A:A,objects!A17) -> 0 | H10: Y | I10: 19 | J10: Dependant | N10: MVP-1 | O10: 7
A11: Campaigns | B11: Source System | C11: A group of marketing activities designed to support a specific business objective or overaching message. | D11: May be used to influence attribution wieghting as contains metadata that might indicate how relevant the content was for the linked outcome. | E11: Use for comparing campaign performance. Used for filtering to activity within a specific campaign or attribute of campaign. | F11: This is defined by the use of monday.com to generate a grouping. each Campaign should have a unique Monday Code. Iideally each campaign should have a clear and distinct audience. Be aligned to a single objective. We expect Asset reuse to be contained to a single campaign. Campaigns may superseed each other if there is a singificant overhall of content or delivery machanisms. In this case there would be multiple Rows representing each version of the campaign. | G11: =COUNTIF(Attributes!A:A,objects!A2) -> 13 | H11: y | I11: 1 | J11: 30 | L11: bps_roi_ro/DSS(Archect review Qlik) | N11: MVP-2
A12: Channels | B12: MRD | C12: A method of Delivering Content/assets to customers. E.G. Email. | D12: May be used to generalise and estimate the proportion of outcomes attributed back to activity. | E12: Use for comparison and filtering on dashboards to compare between channels and compare within a channel. | F12: Each channel represents a different way the customer experiances recieving the Asset. This is a reference table So each channel should be agreed and defined, This should be technology agnostic from BT delivery method. But might be technology relevant for delivery platform, Where BT has control. That is each Social Media platform is a different channel, Within those Ads Vs Organic Would be a different channel. But within Email there wouldn’t be different channels for the different email clients a person may recieve an email with. | G12: =COUNTIF(Attributes!A:A,objects!A3) -> 17 | H12: Y | I12: 2 | J12: =COUNTA(Channels!B:B)-1 -> 22 | N12: MVP-2
A13: Facilitation Tool | B13: MRD | C13: A BT tool that facilitates the delivery of content/asssets to the Customers. | D13: Attribution shouldn’t use this information. | E13: Usefuly for Comparison and Filtering, So understand perfomance of similar channels and campaigns across different platforms. And to Understand within platforms performance. | F13: Each row Represents a single platform. This is a reference table. Some decisions need to be made as to how platform bundles and addons should be Represented. Suggest each row represents the complete tool. All the elements accessible from a single interface/Has a seperate contract/cost/Would be expected to be used by the same person. | G13: =COUNTIF(Attributes!A:A,objects!A4) -> 29 | H13: Y | I13: 3 | J13: 7
A14: Marketing Assets | B14: Source System | C14: This is a piece of content or experiance that would be expected to be engaged with at a single point in time. | D14: May be used to generalise and estimate the proportion of outcomes attributed back to activity. | E14: Useful for comparison within a particular channel to find find grain improvements | F14: Each Row Represents a single piece of content, This may be an email, article, event. Some channel specific examples. Short events / Webinars might be one asset, Longer Events may be split into session. Variations of an email that share a meaningfully different message would be seperate assets. But emails that differ only in personalisation changes would be one asset. An assets should be something that everyone experiances the same way. No two people should have meaningfully different experiances with that asset. | G14: =COUNTIF(Attributes!A:A,objects!A5) -> 59 | H14: Y | I14: 4 | J14: 300 | N14: MVP-2
A15: Audience | B15: Source System | C15: A set of chriteria that defined a group of people who might be targeted for a communication or may be expected to be influenced by an asset. | D15: Purpose here is to provide a linking methodology for Assets where direct influence to individuals is not possible due to the delivery channel. | E15: Not used for Analytics | F15: A specific and complete set of criteria would be contained in a single row. This same audience may be utilised by multiple assets or channels. This wouldn’t result in multiple Audience rows. Multiple audiences criteria may have overlapping members. And audience respresents the complete criteria a communicatino wouldn’t go to some intersection of two audiences, This example would be a third audience. | G15: =COUNTIF(Attributes!A:A,objects!A6) -> 42 | H15: Y | I15: 5 | J15: 100
A16: Opportunities | B16: Source System | C16: The Opportunity to have a sales focussed discussion/process with an individual to sell a specific product, group of products, or package. With an end success for failure result. | D16: This is an outcome to be attributed to influence activities. | E16: Used to show the attributed outcomes | F16: Each Row represents a period of time attempting to sell a to a specific interest for a specific company. This should end in a success or failure. A Second row could represent a further attempt to sell to the same interest to the same company at a different time. E.g. Each yearly renewal. Multiple individuals can be involved with a single opportunity this would be 1 row. Two distinct groups of individuals E.G. different local decision makers at different sites, Could be seperate rows for the same interest at the same company. If it was possible for these to have different outcomes. An Opportunity could be selling multiple Products. Ultimately this should match the current in system opportunity grain. | G16: =COUNTIF(Attributes!A:A,objects!A14) -> 9 | H16: n | I16: 10 | N16: MVP-2
A17: Customer Value Change | B17: Logic to be derived | C17: Point in time changes in customer value taking into account all product/Subscription changes happening at that account. | D17: This is an outcome to be attributed to influence activities. | E17: Used to show the attributed outcomes | F17: Each Row represents a company and a time period for that company, Showing its value change. There should be no overlapping of time periods for that company. Suggestion this is grouped to a monthly time period. I.E. each row represents the value change for a company over a month. If there was no value change then no row needs to exist. | G17: =COUNTIF(Attributes!A:A,objects!A15) -> 8 | H17: n | I17: 11 | N17: Dropped From Scope
A18: Retention | B18: Logic to be derived | C18: Point in Time where companies started & cease to be a customer of BT. | D18: This is an outcome to be attributed to influence activities. | E18: Used to show the attributed outcomes | F18: Each Row represents the point in time that a company changed its status as a customer with each BT Brand. If a company leaves and rejoins and leaves again there would be multiple rows for each of these events. If a company leaves as a BT and EE customer there would be two seperate rows for these events. | G18: =COUNTIF(Attributes!A:A,objects!A16) -> 16 | H18: n | I18: 12 | N18: Dropped From Scope
A19: Attribution Model | B19: Data Science Team | C19: Description of the Model and Run parameters | D19: This is suplimentary information to the main output for the attribution modelling. | E19: Used to manage and identify which model should be used in which circumstance and when models should no longer be shown in the dashboarding views. | F19: Each Row represents an different model or iteration of a model. Model iterations would be where all the data has been recalculated with some meaningful change to input parameters. | G19: =COUNTIF(Attributes!A:A,objects!A18) -> 0 | H19: Y | I19: 13 | J19: 1 | N19: MVP-2
A20: Date Dimension | B20: Derived | C20: Calendar Table that contains all dates, For a unified reference. Expecting something like this already exists close to other analytics use cases. | D20: Used for Date difference calculations and core attribution logic matching | E20: Dashboard Filtering and timeline Dimensions | F20: Each Row Represents a Day | G20: =COUNTIF(Attributes!A:A,objects!A20) -> 7 | H20: Y | I20: 0 | N20: MVP-2
A21: Outcome Change Set | B21: Derived | C21: This is a group of orders for a customer that are grouped as related | D21: Not Used For Attribution | E21: Used for reporting grouping CVC at a customer level and giving additional context to Attribution effects. | G21: =COUNTIF(Attributes!A:A,objects!A21) -> 0 | H21: n | N21: MVP-2
A22: Campaign Company membership | B22: Source System | C22: This identifies the Companies that are part of a campaign and those that are part of control cells for the campaign | D22: Needed for model tuning to align to control cell results analysis and inform model parameter choices | E22: Needed to showcase the Control Cell results within dashboarding. | F22: Each row represents a companies relationship with a campaign. Be that as a member or part of the control cell. | G22: =COUNTIF(Attributes!A:A,objects!A22) -> 8 | H22: n | N22: MVP-2
A23: Campaign Spend | B23: Source System | C23: Gives the costs associated with each campaign | D23: No Used for Attribution | E23: Allows for calculating the investment part of ROI | F23: each row represents a specific spend request for a campaign. | H23: Y

Sheet Attributes
A1: Object | B1: Name | C1: Description | D1: Purpose(modelling) | E1: Purpose(Analytics) | F1: Format | G1: Example Values | H1: Tokenised | I1: Tokenised Reason | J1: Required for POC? | K1: Requiered for MVP? | L1: Available in Core_Orders? | M1: Last Changed Date | N1: Change Description | O1: Column1
A2: Attribution Linking Table | B2: link_id | C2: Unique Identifier for this particular link | F2: PK | J2: MVP | M2: 45937 | N2: Set as PK | O2: =_xlfn.XLOOKUP(Table1[[#This Row],[Name]],'Field name checks'!A:A,'Field name checks'!A:A,"Missing",0) -> Missing
A3: Attribution Linking Table | B3: marketing_activity_id | C3: Identifies the specific marketing activity being linked | F3: FK -> Marketing Activity.Marketing_Activity_ID | J3: MVP | M3: 45947 | N3: Changed Name to marekting activity ID | O3: =_xlfn.XLOOKUP(Table1[[#This Row],[Name]],'Field name checks'!A:A,'Field name checks'!A:A,"Missing",0) -> Missing
A4: Attribution Linking Table | B4: interaction_id | C4: Identifies the specific interaction that is being linked | F4: FK -> Interaction.Interaction_ID | J4: MVP | O4: =_xlfn.XLOOKUP(Table1[[#This Row],[Name]],'Field name checks'!A:A,'Field name checks'!A:A,"Missing",0) -> Missing
A5: Attribution Linking Table | B5: outcome_type | C5: Identifies which outcome table is being linked | E5: used in metric calculations to filter out irrelevant rows. | F5: Picklist | G5: Order - Provide Order - Resign Order - Mixed Order - Churn Opportunity - Created Opportunity - Closed Won | J5: MVP | O5: =_xlfn.XLOOKUP(Table1[[#This Row],[Name]],'Field name checks'!A:A,'Field name checks'!A:A,"Missing",0) -> Missing
A6: Attribution Linking Table | B6: outcome_id | C6: Identifies the specific outcome within that table that is linked. | F6: FK -> Outcome_Type.Outcome_ID | J6: MVP | O6: =_xlfn.XLOOKUP(Table1[[#This Row],[Name]],'Field name checks'!A:A,'Field name checks'!A:A,"Missing",0) -> Missing
A7: Attribution Linking Table | B7: company_id | C7: Identifies the company that carried out the interaction and is related to the outcome. | F7: FK -> Company.Company_ID | J7: MVP | O7: =_xlfn.XLOOKUP(Table1[[#This Row],[Name]],'Field name checks'!A:A,'Field name checks'!A:A,"Missing",0) -> Missing
A8: Attribution Linking Table | B8: person_id | C8: Identifies the Person related to the activity or interaction. | F8: FK -> Person.Person_ID | J8: MVP | O8: =_xlfn.XLOOKUP(Table1[[#This Row],[Name]],'Field name checks'!A:A,'Field name checks'!A:A,"Missing",0) -> Missing
A9: Attribution Linking Table | B9: relation_type | C9: Classify how the Activity was related to the outcome. Its possible there were multiple methods to associate the activity with the outcome. This identifies the most confident of linkage types. | D9: Used as a paremeter to govern how much attribution is given to this link. | F9: Picklist | G9: Direct - Activity can be directly linked to the outcome I.E. they bought on the call. Known Person - The person that carried out the interaction/was targeted by activity is linked to the company that had the outcome. Known company - The company that was targeted by activity or carried out the interaction could be confidently identified and that company is linked to the outcome. Inferred company - The activity was likely carried out be the company that is linked to the activity. Inferred via Audience - The individual / company was included in the audience for the marketing activity. | J9: MVP | O9: =_xlfn.XLOOKUP(Table1[[#This Row],[Name]],'Field name checks'!A:A,'Field name checks'!A:A,"Missing",0) -> Missing
A10: Attribution Linking Table | B10: time_lag | C10: Time Between the Activity and the outcome * modelling may prefer to calculate from source fields. | D10: Used as a paremeter to govern how much attribution is given to this link. | F10: Time Difference | J10: MVP | O10: =_xlfn.XLOOKUP(Table1[[#This Row],[Name]],'Field name checks'!A:A,'Field name checks'!A:A,"Missing",0) -> Missing
A11: Attribution Linking Table | B11: product_yca_tier | C11: Identifiest the Tier of the product that is the closest common parent to the product of the order and the product of the Campaign or Asset. | D11: Used as a paremeter to govern how much attribution is given to this link. | E11: Not Relevant for analytics | F11: List of Values [Tiers} | J11: MVP | O11: =_xlfn.XLOOKUP(Table1[[#This Row],[Name]],'Field name checks'!A:A,'Field name checks'!A:A,"Missing",0) -> Missing
A12: Attribution Linking Table | B12: company_yca_type | C12: Gives the company_business_type of the Youngest Common Ancestor of the company the order was associated and the company assoicated to the activity. | D12: Used as a paremeter to govern how much attribution is given to this link. | E12: Not Relevant for analytics | F12: List of value [Company Types] | J12: MVP | O12: =_xlfn.XLOOKUP(Table1[[#This Row],[Name]],'Field name checks'!A:A,'Field name checks'!A:A,"Missing",0) -> Missing
A13: Attribution Model Output Table | B13: model_output_id | C13: Unique Identifier for the model output given for this link and model. | F13: ID - PK | J13: MVP | O13: =_xlfn.XLOOKUP(Table1[[#This Row],[Name]],'Field name checks'!A:A,'Field name checks'!A:A,"Missing",0) -> Missing
A14: Attribution Model Output Table | B14: link_id | C14: Which is the link this result relates to | F14: ID - FK | J14: MVP | O14: =_xlfn.XLOOKUP(Table1[[#This Row],[Name]],'Field name checks'!A:A,'Field name checks'!A:A,"Missing",0) -> Missing
A15: Attribution Model Output Table | B15: model_id | C15: Which Model has provided this result | F15: ID - FK | J15: MVP | O15: =_xlfn.XLOOKUP(Table1[[#This Row],[Name]],'Field name checks'!A:A,'Field name checks'!A:A,"Missing",0) -> Missing
A16: Attribution Model Output Table | B16: attribution_weight | C16: What is the proportion of the outcome that was caused by the activity as calculated by the model. | F16: Float | G16: 0.05 | J16: MVP | O16: =_xlfn.XLOOKUP(Table1[[#This Row],[Name]],'Field name checks'!A:A,'Field name checks'!A:A,"Missing",0) -> Missing
A17: Attrribution Model | B17: model_id | C17: Unique Identifier for the model | F17: ID - PK | J17: If Available | O17: =_xlfn.XLOOKUP(Table1[[#This Row],[Name]],'Field name checks'!A:A,'Field name checks'!A:A,"Missing",0) -> Missing
A18: Attrribution Model | B18: model_name | C18: Name given the the model | E18: Used to select which attribution model is used for attribution calculations | F18: String | G18: V01.0_Rules_Based_with_Guardrails | J18: If Available | O18: =_xlfn.XLOOKUP(Table1[[#This Row],[Name]],'Field name checks'!A:A,'Field name checks'!A:A,"Missing",0) -> Missing
A19: Attrribution Model | B19: model_start_date | C19: When was the model usable from | F19: Date | J19: If Available | O19: =_xlfn.XLOOKUP(Table1[[#This Row],[Name]],'Field name checks'!A:A,'Field name checks'!A:A,"Missing",0) -> Missing
A20: Attrribution Model | B20: model_end_date | C20: When does the model cease to be useable. | F20: Date | J20: If Available | O20: =_xlfn.XLOOKUP(Table1[[#This Row],[Name]],'Field name checks'!A:A,'Field name checks'!A:A,"Missing",0) -> Missing
A21: Attrribution Model | B21: model_status | C21: is the model validated and usable, or retired | E21: Used to confirm if this model is appropriate to use in Dashboarding. | F21: Picklist | J21: If Available | O21: =_xlfn.XLOOKUP(Table1[[#This Row],[Name]],'Field name checks'!A:A,'Field name checks'!A:A,"Missing",0) -> Missing
A22: Attrribution Model | B22: model_type | C22: Classifies the models that are produced by the modelling team by which techniques they use | D22: Output from the modelling team | E22: Used to allow end users to select the appropriate model and understand at a high level how that model is approaching attribution. | F22: Picklist | G22: Rules based, learned, TBC from Modelling Team | J22: If Available | O22: =_xlfn.XLOOKUP(Table1[[#This Row],[Name]],'Field name checks'!A:A,'Field name checks'!A:A,"Missing",0) -> Missing
A23: Attrribution Model | B23: outcome_used | C23: Which outcome is this model Attributing for | F23: Picklist | G23: Raised Orders, Completed Orders, Customer Value Change, Churn, leads, Lead Conversion | J23: If Available | O23: =_xlfn.XLOOKUP(Table1[[#This Row],[Name]],'Field name checks'!A:A,'Field name checks'!A:A,"Missing",0) -> Missing
A24: Attrribution Model | B24: model_owner | C24: Current Owner of the model implimentation | F24: String | G24: Petros | J24: If Available | O24: =_xlfn.XLOOKUP(Table1[[#This Row],[Name]],'Field name checks'!A:A,'Field name checks'!A:A,"Missing",0) -> Missing
A25: Audience | B25: audience_id | O25: =_xlfn.XLOOKUP(Table1[[#This Row],[Name]],'Field name checks'!A:A,'Field name checks'!A:A,"Missing",0) -> Missing
A26: Audience | B26: name | C26: Friendly Name of the audience | O26: =_xlfn.XLOOKUP(Table1[[#This Row],[Name]],'Field name checks'!A:A,'Field name checks'!A:A,"Missing",0) -> Missing
A27: Audience | B27: type | C27: How is this audience identified | O27: =_xlfn.XLOOKUP(Table1[[#This Row],[Name]],'Field name checks'!A:A,'Field name checks'!A:A,"Missing",0) -> Missing
A28: Audience | B28: audience_criteria_description | C28: An description of the requirements for the audience to fulfil | O28: =_xlfn.XLOOKUP(Table1[[#This Row],[Name]],'Field name checks'!A:A,'Field name checks'!A:A,"Missing",0) -> Missing
A29: Audience | B29: audience_criteria_technical | C29: The technical implimentation of these audience requirements. | O29: =_xlfn.XLOOKUP(Table1[[#This Row],[Name]],'Field name checks'!A:A,'Field name checks'!A:A,"Missing",0) -> Missing
A30: Audience | B30: propensity_model_used | C30: Identifies the propensity model that is used as part of the audience selection criteria. This would be a FK to another table. | D30: N/A | E30: Dimensions for filter and comparison, Gives the end user the ability to understand the effectiveness of the propensity models. | O30: =_xlfn.XLOOKUP(Table1[[#This Row],[Name]],'Field name checks'!A:A,'Field name checks'!A:A,"Missing",0) -> Missing
A31: Audience | B31: size_individuals | C31: The Estimated or actual count of individuals that form this audience. | O31: =_xlfn.XLOOKUP(Table1[[#This Row],[Name]],'Field name checks'!A:A,'Field name checks'!A:A,"Missing",0) -> Missing
A32: Audience | B32: size_companies | C32: The Estimated or actual count of Companies that form this audience. *Company Granularity to be determined | O32: =_xlfn.XLOOKUP(Table1[[#This Row],[Name]],'Field name checks'!A:A,'Field name checks'!A:A,"Missing",0) -> Missing
A33: Campaigns | B33: campaign_id | C33: Primary Identified for a campaign, This could either be the Monday code or a GCP generated ID, using the Monday code as a proxy identifier. | F33: ID - PK | J33: MVP | O33: =_xlfn.XLOOKUP(Table1[[#This Row],[Name]],'Field name checks'!A:A,'Field name checks'!A:A,"Missing",0) -> campaign_id
A34: Campaigns | B34: campaign_name | C34: The Unique business understandable short name of the campaign. | E34: Dimension for Filter / Comparison | F34: String | J34: MVP | O34: =_xlfn.XLOOKUP(Table1[[#This Row],[Name]],'Field name checks'!A:A,'Field name checks'!A:A,"Missing",0) -> campaign_name
A35: Campaigns | B35: dmo_monday_id | C35: This is Unique identifier in the DMO board for tracking campaign creation. Also used within marketo and other systems as the campaign Identifier. | M35: 45959 | N35: Added | O35: =_xlfn.XLOOKUP(Table1[[#This Row],[Name]],'Field name checks'!A:A,'Field name checks'!A:A,"Missing",0) -> dmo_monday_id
A36: Campaigns | B36: activity_status | C36: Current build status of the activity (e.g., Not started, In progress) | E36: Hidden filter to exclude irrelevant campaings from views. | G36: Not Started; In progress; Stuck; | M36: 45959 | N36: Added | O36: =_xlfn.XLOOKUP(Table1[[#This Row],[Name]],'Field name checks'!A:A,'Field name checks'!A:A,"Missing",0) -> activity_status
A37: Campaigns | B37: marketing_lead_name | C37: Primary person responsible for the activity | E37: Dimension for Filter / Comparison | M37: 45959 | N37: Added | O37: =_xlfn.XLOOKUP(Table1[[#This Row],[Name]],'Field name checks'!A:A,'Field name checks'!A:A,"Missing",0) -> marketing_lead_name
A38: Campaigns | B38: contributer_name | C38: Additional team members contributing to the activity. | E38: Dimension for Filter | M38: 45959 | N38: Added | O38: =_xlfn.XLOOKUP(Table1[[#This Row],[Name]],'Field name checks'!A:A,'Field name checks'!A:A,"Missing",0) -> contributer_name
A39: Campaigns | B39: campaign_planned_start_date | C39: Planned Start Date of the activity. (Needs confirmation if this is correct) | E39: Dimension for Filter | M39: 45959 | N39: Added | O39: =_xlfn.XLOOKUP(Table1[[#This Row],[Name]],'Field name checks'!A:A,'Field name checks'!A:A,"Missing",0) -> campaign_planned_start_date
A40: Campaigns | B40: campaign_live_date | C40: Date the campaign First went live and it was possible for a person to interact with the campaigns content. | E40: Dimension for Filter | M40: 45959 | N40: Added | O40: =_xlfn.XLOOKUP(Table1[[#This Row],[Name]],'Field name checks'!A:A,'Field name checks'!A:A,"Missing",0) -> campaign_live_date
A41: Campaigns | B41: engaged_team_name | C41: Team or department executing the activity. | E41: Dimension for Filter / Comparison | M41: 45967 | N41: Updated Field name | O41: =_xlfn.XLOOKUP(Table1[[#This Row],[Name]],'Field name checks'!A:A,'Field name checks'!A:A,"Missing",0) -> engaged_team_name
A42: Campaigns | B42: campaign_summary | C42: Brief description or summary of the activity/campaign | E42: Tooltip or description on campaign view | M42: 45959 | N42: Added | O42: =_xlfn.XLOOKUP(Table1[[#This Row],[Name]],'Field name checks'!A:A,'Field name checks'!A:A,"Missing",0) -> campaign_summary
A43: Campaigns | B43: engagement_stage_classification | C43: Engagement classification (e.g., Engage, Explore, Evaluate). | E43: Dimension for Filter / Comparison | M43: 45959 | N43: Added | O43: =_xlfn.XLOOKUP(Table1[[#This Row],[Name]],'Field name checks'!A:A,'Field name checks'!A:A,"Missing",0) -> engagement_stage_classification
A44: Campaigns | B44: activity_type | C44: Type of marketing activity (e.g., Event, Campaign). | E44: Dimension for Filter / Comparison | M44: 45959 | N44: Added | O44: =_xlfn.XLOOKUP(Table1[[#This Row],[Name]],'Field name checks'!A:A,'Field name checks'!A:A,"Missing",0) -> activity_type
A45: Campaigns | B45: impacted_segment_name | C45: Target segment or business function. | E45: Dimension for Filter / Comparison, Might be superseeded by the business unit field on the company / link object. | F45: Multi Value Picklist | G45: SMB, CEC, CPS, Global, Wholesales | M45: 45967 | N45: Updated Field name | O45: =_xlfn.XLOOKUP(Table1[[#This Row],[Name]],'Field name checks'!A:A,'Field name checks'!A:A,"Missing",0) -> impacted_segment_name
A46: Campaigns | B46: campaign_theme_name | C46: Marketing theme or focus area. | E46: Dimension for Filter / Comparison | M46: 45967 | N46: Updated Field name | O46: =_xlfn.XLOOKUP(Table1[[#This Row],[Name]],'Field name checks'!A:A,'Field name checks'!A:A,"Missing",0) -> campaign_theme_name
A47: Campaigns | B47: product_area | C47: Identifies the product or product area the campaign is targetting | E47: Dimension for Filter / Comparison | M47: 45959 | N47: Added | O47: =_xlfn.XLOOKUP(Table1[[#This Row],[Name]],'Field name checks'!A:A,'Field name checks'!A:A,"Missing",0) -> product_area
A48: Campaigns | B48: impacted_region | C48: Geographical region targeted by the activity | E48: Dimension for Filter / Comparison, Might be superseeded by the location on the company or person object although this data may not be as well populated. | M48: 45967 | N48: Updated Field name | O48: =_xlfn.XLOOKUP(Table1[[#This Row],[Name]],'Field name checks'!A:A,'Field name checks'!A:A,"Missing",0) -> impacted_region
A49: Campaigns | B49: strategic_pillar | C49: Strategic objective supported by the activity | E49: Dimension for Filter / Comparison | M49: 45959 | N49: Added | O49: =_xlfn.XLOOKUP(Table1[[#This Row],[Name]],'Field name checks'!A:A,'Field name checks'!A:A,"Missing",0) -> strategic_pillar
A50: Campaigns | B50: campaign_purpose | C50: What part of the customer lifecycle is being targeted | E50: Dimension for Filter / Comparison | M50: 45967 | N50: Updated Field name | O50: =_xlfn.XLOOKUP(Table1[[#This Row],[Name]],'Field name checks'!A:A,'Field name checks'!A:A,"Missing",0) -> campaign_purpose
A51: Campaigns | B51: business_vertical | C51: Industry vertical targeted | E51: Dimension for Filter / Comparison, May be superseeded by the industry or vertical information on the company object depending on the dashboard context. | M51: 45967 | N51: Updated Field name | O51: =_xlfn.XLOOKUP(Table1[[#This Row],[Name]],'Field name checks'!A:A,'Field name checks'!A:A,"Missing",0) -> business_vertical
A52: Campaigns | B52: partner_name | C52: Company that is partnering, supporting, or running the campaign. | E52: Dimension for Filter / Comparison | M52: 45967 | N52: Updated Field name | O52: =_xlfn.XLOOKUP(Table1[[#This Row],[Name]],'Field name checks'!A:A,'Field name checks'!A:A,"Missing",0) -> partner_name
A53: Campaigns | B53: agency_support_ind | C53: Indicates if external team or agency support is required | E53: Dimension for Filter / Comparison | M53: 45967 | N53: Updated Field name | O53: =_xlfn.XLOOKUP(Table1[[#This Row],[Name]],'Field name checks'!A:A,'Field name checks'!A:A,"Missing",0) -> agency_support_ind
A54: Campaigns | B54: agency_name | C54: Name of the supporting team or agency | E54: Dimension for Filter / Comparison | M54: 45959 | N54: Added | O54: =_xlfn.XLOOKUP(Table1[[#This Row],[Name]],'Field name checks'!A:A,'Field name checks'!A:A,"Missing",0) -> agency_name
A55: Campaigns | B55: brand_name | C55: Brand associated with the activity | D55: Allow limiting or wieghting of attribution based on Brand matching between activity and outcome. | E55: Dimension for Filter / Comparison | G55: BT; EE; BT and EE; | J55: MVP | M55: 45967 | N55: Updated Field name | O55: =_xlfn.XLOOKUP(Table1[[#This Row],[Name]],'Field name checks'!A:A,'Field name checks'!A:A,"Missing",0) -> brand_name
A56: Campaigns | B56: estimated_outcome_gross_margin | C56: Estimated gross margin from marketing-influenced wins | E56: Could be utilised to showcase the campaign target against a measure of actually. showing which campaigns are achieving thier targets. | M56: 45959 | N56: Added | O56: =_xlfn.XLOOKUP(Table1[[#This Row],[Name]],'Field name checks'!A:A,'Field name checks'!A:A,"Missing",0) -> estimated_outcome_gross_margin
A57: Campaigns | B57: estimated_outcome_sov | C57: Share of voice from marketing-influenced wins | E57: Could be utilised to showcase the campaign target against a measure of actually. showing which campaigns are achieving thier targets. | M57: 45959 | N57: Added | O57: =_xlfn.XLOOKUP(Table1[[#This Row],[Name]],'Field name checks'!A:A,'Field name checks'!A:A,"Missing",0) -> estimated_outcome_sov
A58: Campaigns | B58: estimated_outcome_roix1 | C58: Return on investment ratio | E58: Could be utilised to showcase the campaign target against a measure of actually. showing which campaigns are achieving thier targets. | M58: 45959 | N58: Added | O58: =_xlfn.XLOOKUP(Table1[[#This Row],[Name]],'Field name checks'!A:A,'Field name checks'!A:A,"Missing",0) -> estimated_outcome_roix1
A59: Campaigns | B59: overall_timeline_start | C59: Needs confirmation on what this will mean | M59: 45959 | N59: Added | O59: =_xlfn.XLOOKUP(Table1[[#This Row],[Name]],'Field name checks'!A:A,'Field name checks'!A:A,"Missing",0) -> overall_timeline_start
A60: Campaigns | B60: overall_timeline_end | C60: Needs confirmation on what this will mean | M60: 45959 | N60: Added | O60: =_xlfn.XLOOKUP(Table1[[#This Row],[Name]],'Field name checks'!A:A,'Field name checks'!A:A,"Missing",0) -> overall_timeline_end
A61: Campaigns | B61: outcome_linear_roi_flag | C61: Indicates if ROI is linear (Yes/No) | M61: 45959 | N61: Added | O61: =_xlfn.XLOOKUP(Table1[[#This Row],[Name]],'Field name checks'!A:A,'Field name checks'!A:A,"Missing",0) -> outcome_linear_roi_flag
A62: Campaigns | B62: monday_record_creation_dtm | C62: Date the Campaign was created (in Monday.com) | F62: Date | J62: If Available | M62: 45959 | N62: Added | O62: =_xlfn.XLOOKUP(Table1[[#This Row],[Name]],'Field name checks'!A:A,'Field name checks'!A:A,"Missing",0) -> monday_record_creation_dtm
A63: Campaigns | B63: product_id | C63: Identifies the Product the Campaign Is Targeting | D63: Feeds the marketing product to outcome product comparison which ultimately informs some of the wieght of the link attribution | E63: Dimension for Filter / Comparison, We may also want to group / filter on products higher up the hierachy. | F63: FK -> Product.Product_ID | J63: MVP | O63: =_xlfn.XLOOKUP(Table1[[#This Row],[Name]],'Field name checks'!A:A,'Field name checks'!A:A,"Missing",0) -> Missing
A64: Campaigns | B64: source_table | C64: Identifies the GCP table that this Row is sourced from | F64: GCP Table Reference | J64: MVP | O64: =_xlfn.XLOOKUP(Table1[[#This Row],[Name]],'Field name checks'!A:A,'Field name checks'!A:A,"Missing",0) -> Missing
A65: Campaigns | B65: source_id_field | C65: Identifies the PK field of that table. | F65: String | J65: MVP | O65: =_xlfn.XLOOKUP(Table1[[#This Row],[Name]],'Field name checks'!A:A,'Field name checks'!A:A,"Missing",0) -> Missing
A66: Campaigns | B66: source_id | C66: The Source Table PK Value. | F66: FK -> Source_Table. Source_ID_Field | J66: MVP | O66: =_xlfn.XLOOKUP(Table1[[#This Row],[Name]],'Field name checks'!A:A,'Field name checks'!A:A,"Missing",0) -> Missing
A67: Channels | B67: channel_key | C67: GCP Generated | D67: PK to be referenced by other objects. | F67: ID - PK | J67: Y | M67: 45973 | N67: Changed name from channel_id to channel_key by Mahesh | O67: =_xlfn.XLOOKUP(Table1[[#This Row],[Name]],'Field name checks'!A:A,'Field name checks'!A:A,"Missing",0) -> Missing
A68: Channels | B68: channel_name | C68: Name Representing the channel | E68: Used for grouping and comparison within dashboards. | F68: String | J68: Y | M68: 45953 | N68: Updated Name to Channel Name to avoid field clashing | O68: =_xlfn.XLOOKUP(Table1[[#This Row],[Name]],'Field name checks'!A:A,'Field name checks'!A:A,"Missing",0) -> Missing
A69: Channels | B69: channel_group | C69: The Broad category of communication styles this channel is part of. | E69: Used for grouping and comparison within dashboards. | F69: Enumerated String | G69: Above the Line - Broad Mass market campaigns to a loosely or undefined audience. Below the Line - Targeted Communications to a known audience. Sales - One to One communications to an individual to support an existing or potential sales opportunity. | J69: Y | M69: 45973 | N69: Changed name from group to channel_group by Mahesh | O69: =_xlfn.XLOOKUP(Table1[[#This Row],[Name]],'Field name checks'!A:A,'Field name checks'!A:A,"Missing",0) -> Missing
A70: Channels | B70: channel_type | C70: Another way we could group channels is by the different high level delivery mechanisms involved. | E70: Dimension for Filter / Comparison | F70: Enumerated String | G70: Physical - Channel is delivered via a physical object, I.E. Print, DM ect. Digital - Channel is delivered digitally Conversation - Channel is delivered by a BT representative as part of a conversation. | J70: Y | M70: 45973 | N70: Changed name from type to channel_type by Mahesh | O70: =_xlfn.XLOOKUP(Table1[[#This Row],[Name]],'Field name checks'!A:A,'Field name checks'!A:A,"Missing",0) -> Missing
A71: Channels | B71: communication_mode | C71: Identifies if this is a push or pull communication. | E71: Helps understanding which attributes we would expect in the related marketing activities. | G71: Push Pull | J71: Y | O71: =_xlfn.XLOOKUP(Table1[[#This Row],[Name]],'Field name checks'!A:A,'Field name checks'!A:A,"Missing",0) -> Missing
A72: Attribution Linking Table | B72: company_trading_unit | C72: Describes which business area in BT this interaction to outcome relates to. Ultimately the market channel of the account. | D72: Different market channel may have different parameter rulesets. | E72: A key filter in most dashboards as almost all audiences will care about only companis from a single group in this list. | G72: SMB, CPS, Wholesale, Global | J72: MVP | M72: 45959 | N72: Added | O72: =_xlfn.XLOOKUP(Table1[[#This Row],[Name]],'Field name checks'!A:A,'Field name checks'!A:A,"Missing",0) -> Missing
A73: Company | B73: company_source_table_name | C73: Identifies the GCP table that this Row is sourced from | F73: GCP Table Reference | J73: Y | M73: 45973 | N73: Changed name from source_table to company_source_table_name by Mahesh | O73: =_xlfn.XLOOKUP(Table1[[#This Row],[Name]],'Field name checks'!A:A,'Field name checks'!A:A,"Missing",0) -> Missing
A74: Company | B74: company_source_id_field_name | C74: Identifies the PK field of that table. | F74: String | J74: Y | M74: 45973 | N74: Changed name from source_id_field to company_source_id_field_name by Mahesh | O74: =_xlfn.XLOOKUP(Table1[[#This Row],[Name]],'Field name checks'!A:A,'Field name checks'!A:A,"Missing",0) -> Missing
A75: Company | B75: company_source_field_value | C75: The Source Table PK Value. | F75: FK -> Source_Table. Source_ID_Field | J75: Y | M75: 45973 | N75: Changed name from source_id to company_source_field_value by Mahesh
A76: Company | B76: parent_company_id | F76: FK -> Company.Company_ID | J76: N | O76: =_xlfn.XLOOKUP(Table1[[#This Row],[Name]],'Field name checks'!A:A,'Field name checks'!A:A,"Missing",0) -> Missing
A77: Company | B77: company_business_type | C77: Describes the granularity/ Type of account at a size level. Also how BT thinks about this account. Used to understand the hierarchy. | D77: Used as part of the linking strategy to understand how closely linked a marketing activity is to an outcome. We may look at the largest grain of company needed for form the link. | E77: Not Relevant for analytics | G77: CUG, Billing Account, SAC, World Key, LE | J77: Y | O77: =_xlfn.XLOOKUP(Table1[[#This Row],[Name]],'Field name checks'!A:A,'Field name checks'!A:A,"Missing",0) -> Missing
A78: Date Dimension | B78: date_key | C78: This is the Date Primary Key | O78: =_xlfn.XLOOKUP(Table1[[#This Row],[Name]],'Field name checks'!A:A,'Field name checks'!A:A,"Missing",0) -> Missing
A79: Date Dimension | B79: date | C79: Actual Date being represented | O79: =_xlfn.XLOOKUP(Table1[[#This Row],[Name]],'Field name checks'!A:A,'Field name checks'!A:A,"Missing",0) -> Missing
A80: Date Dimension | B80: financial_year | C80: Which financial Year this date falls within | O80: =_xlfn.XLOOKUP(Table1[[#This Row],[Name]],'Field name checks'!A:A,'Field name checks'!A:A,"Missing",0) -> Missing
A81: Date Dimension | B81: financial_quarter | C81: Which Financial Quarter this date falls into. | O81: =_xlfn.XLOOKUP(Table1[[#This Row],[Name]],'Field name checks'!A:A,'Field name checks'!A:A,"Missing",0) -> Missing
A82: Date Dimension | B82: financial_month_number | C82: Month Number within BT Financial Year. | O82: =_xlfn.XLOOKUP(Table1[[#This Row],[Name]],'Field name checks'!A:A,'Field name checks'!A:A,"Missing",0) -> Missing
A83: Date Dimension | B83: is_weekend | O83: =_xlfn.XLOOKUP(Table1[[#This Row],[Name]],'Field name checks'!A:A,'Field name checks'!A:A,"Missing",0) -> Missing
A84: Date Dimension | B84: is_holiday | O84: =_xlfn.XLOOKUP(Table1[[#This Row],[Name]],'Field name checks'!A:A,'Field name checks'!A:A,"Missing",0) -> Missing
A85: Facilitation Tool | B85: facilitation_tool_name | C85: Name of the tool | F85: String | O85: =_xlfn.XLOOKUP(Table1[[#This Row],[Name]],'Field name checks'!A:A,'Field name checks'!A:A,"Missing",0) -> Missing
A86: Facilitation Tool | B86: owner | C86: The BT team member that is responsible for this tool | F86: String | O86: =_xlfn.XLOOKUP(Table1[[#This Row],[Name]],'Field name checks'!A:A,'Field name checks'!A:A,"Missing",0) -> Missing
A87: Marketing Activity | B87: name | C87: Optional Name of the activity, might not be needed may come from asset + Campaign. | F87: String | J87: If Available | O87: =_xlfn.XLOOKUP(Table1[[#This Row],[Name]],'Field name checks'!A:A,'Field name checks'!A:A,"Missing",0) -> Missing
A88: Marketing Activity | B88: source_id_field | C88: Identifies the PK field of that table. | F88: String | J88: MVP | O88: =_xlfn.XLOOKUP(Table1[[#This Row],[Name]],'Field name checks'!A:A,'Field name checks'!A:A,"Missing",0) -> Missing
A89: Interactions | B89: interaction_id | C89: Unique Identifier for the Interaction | J89: MVP | O89: =_xlfn.XLOOKUP(Table1[[#This Row],[Name]],'Field name checks'!A:A,'Field name checks'!A:A,"Missing",0) -> Missing
A90: Interactions | B90: interaction_type | C90: What was the type of intereaction. E.G. Open, Click, Visit, Call,… | E90: Dimension for Filter / Comparison | J90: MVP | O90: =_xlfn.XLOOKUP(Table1[[#This Row],[Name]],'Field name checks'!A:A,'Field name checks'!A:A,"Missing",0) -> Missing
A91: Interactions | B91: interaction_date | C91: When did this interaction happen. | E91: Key field for marketing focussed dashboard date filters and and over time trends. | J91: MVP | O91: =_xlfn.XLOOKUP(Table1[[#This Row],[Name]],'Field name checks'!A:A,'Field name checks'!A:A,"Missing",0) -> Missing
A92: Interactions | B92: interaction_dur | C92: How long did the interaction last. | F92: INTERVAL | G92: 1-2 3 4:5:6.789999 https://cloud.google.com/bigquery/docs/reference/standard-sql/interval_functions | J92: If Available | O92: =_xlfn.XLOOKUP(Table1[[#This Row],[Name]],'Field name checks'!A:A,'Field name checks'!A:A,"Missing",0) -> Missing
A93: Interactions | B93: follow_from_interaction_id | C93: If interaction came from a separate interaction. I.E. click on link -> View Webpage -> Submit Form | D93: Allows for direct attribution chains of interactions through to orders. So we can see all the interactions in a journey that lead to an outcome. | F93: FK -> interactions.interaction_id | J93: If Available | O93: =_xlfn.XLOOKUP(Table1[[#This Row],[Name]],'Field name checks'!A:A,'Field name checks'!A:A,"Missing",0) -> Missing
A94: Interactions | B94: marketing_activity_id | C94: What was the Activity this interaction is related to. | F94: FK -> Marketing Activity.marketing_activity_id | J94: MVP | O94: =_xlfn.XLOOKUP(Table1[[#This Row],[Name]],'Field name checks'!A:A,'Field name checks'!A:A,"Missing",0) -> Missing
A95: Interactions | B95: interacted_person_id | C95: Identifies the person that carried out the interaction. | F95: FK -> Person.Person_ID | J95: MVP | O95: =_xlfn.XLOOKUP(Table1[[#This Row],[Name]],'Field name checks'!A:A,'Field name checks'!A:A,"Missing",0) -> Missing
A96: Interactions | B96: interacted_company_id | C96: Identifies the company that carried out the interaction. | F96: FK -> Company.Company_ID | J96: MVP | O96: =_xlfn.XLOOKUP(Table1[[#This Row],[Name]],'Field name checks'!A:A,'Field name checks'!A:A,"Missing",0) -> Missing
A97: Interactions | B97: identification_method_type | C97: What method was used to identify the individual or company for this interaction. | G97: Outbound Known Person - We sent a communication to a specific person and so subsiquent actions can be linked to the same person. Outbound Known Company - We sent a communication to a specific company and so Subsciquent actions can be linked to that company. We do not know which person in the company recieved the communication. Self Identification - The person Identified themselves through login or form submission. Visitor Matching Person - Other Interactions associated with the same visitor have been identified through Self Identification or Known communications. So we can infer this is the same person. Visitor Matching Company - Other Interactions associated with the same visitor have been identified through Self Identification or Known communications. So we can infer this is the same Company. IP Company Match - IP Associated with this interaction has been consistantly matched with the same company, So we have infered the company through this IP. | J97: MVP | M97: 13/10/2025 | N97: Updated Example Values and Added Descriptions. | O97: =_xlfn.XLOOKUP(Table1[[#This Row],[Name]],'Field name checks'!A:A,'Field name checks'!A:A,"Missing",0) -> Missing
A98: Interactions | B98: data_source_name | C98: Which system tracked this interaction | J98: MVP | O98: =_xlfn.XLOOKUP(Table1[[#This Row],[Name]],'Field name checks'!A:A,'Field name checks'!A:A,"Missing",0) -> Missing
A99: Interactions | B99: source_table | C99: Identifies the GCP table that this Row is sourced from | F99: GCP Table Reference | J99: MVP | O99: =_xlfn.XLOOKUP(Table1[[#This Row],[Name]],'Field name checks'!A:A,'Field name checks'!A:A,"Missing",0) -> Missing
A100: Interactions | B100: source_id_field | C100: Identifies the PK field of that table. | F100: String | J100: MVP | O100: =_xlfn.XLOOKUP(Table1[[#This Row],[Name]],'Field name checks'!A:A,'Field name checks'!A:A,"Missing",0) -> Missing
...

Sheet Field name checks
A1: Use Case DP Attribute Name
A2: campaign_name | B2: =_xlfn.XLOOKUP(A2,Attributes!O:O,Attributes!O:O,"Missing") -> campaign_name
A3: campaign_id | B3: =_xlfn.XLOOKUP(A3,Attributes!O:O,Attributes!O:O,"Missing") -> campaign_id
A4: dmo_monday_id | B4: =_xlfn.XLOOKUP(A4,Attributes!O:O,Attributes!O:O,"Missing") -> dmo_monday_id
A5: activity_status | B5: =_xlfn.XLOOKUP(A5,Attributes!O:O,Attributes!O:O,"Missing") -> activity_status
A6: marketing_lead_name | B6: =_xlfn.XLOOKUP(A6,Attributes!O:O,Attributes!O:O,"Missing") -> marketing_lead_name
A7: contributer_name | B7: =_xlfn.XLOOKUP(A7,Attributes!O:O,Attributes!O:O,"Missing") -> contributer_name
A8: campaign_planned_start_date | B8: =_xlfn.XLOOKUP(A8,Attributes!O:O,Attributes!O:O,"Missing") -> campaign_planned_start_date
A9: campaign_live_date | B9: =_xlfn.XLOOKUP(A9,Attributes!O:O,Attributes!O:O,"Missing") -> campaign_live_date
A10: engaged_team_name | B10: =_xlfn.XLOOKUP(A10,Attributes!O:O,Attributes!O:O,"Missing") -> engaged_team_name
A11: campaign_summary | B11: =_xlfn.XLOOKUP(A11,Attributes!O:O,Attributes!O:O,"Missing") -> campaign_summary
A12: engagement_stage_classification | B12: =_xlfn.XLOOKUP(A12,Attributes!O:O,Attributes!O:O,"Missing") -> engagement_stage_classification
A13: activity_type | B13: =_xlfn.XLOOKUP(A13,Attributes!O:O,Attributes!O:O,"Missing") -> activity_type
... A35: active_flag | B35: =_xlfn.XLOOKUP(A35,Attributes!O:O,Attributes!O:O,"Missing") -> Missing

Sheet Sheet1
A1: Activity ID | B1: Outcome ID | C1: Outcome Type | D1: Link ID | E1: Interaction | F1: Contact | G1: Company | H1: Relation Type | I1: Time Lag (Days) | K1: Weight | M1: Outcome Value | N1: Attributed Amount | P1: Sales Order Value | Q1: Sales Order Value Gross Margin | R1: Initial Contract Value | S1: Initial Contract Value Gross margin | T1: Average Revenue per Unit
A2: 1 | B2: 1 | C2: Opportunty Created | D2: a | E2: 1 | F2: 1 | G2: 1 | H2: Direct Through Order | I2: 10 | K2: 0.1 | M2: 1000 | N2: =M2*K2 -> 100
A3: 1 | B3: 2 | C3: Opportunty Won | D3: b | E3: 1 | F3: 5 | G3: 2 | H3: Through Company | I3: 200 | K3: 0.02 | M3: 250 | N3: =M3*K3 -> 5
A4: 1 | B4: 2 | C4: Opportunty Won | D4: h | E4: 2 | G4: 3 | H4: Inferred company | I4: 15 | K4: 0.6 | M4: 250 | N4: =M4*K4 -> 150
A5: 2 | B5: 1 | C5: Opportunty Created | D5: c | E5: 3 | G5: 4 | H5: Through Contact & Company | I5: 1 | K5: 0.52 | M5: 1000 | N5: =M5*K5 -> 520
A6: 3 | B6: 3 | C6: Orders | D6: d | E6: 4 | F6: 6 | G6: 5 | H6: Through Company | I6: 0 | K6: 0.1 | M6: 555 | N6: =M6*K6 -> 55.5
A7: 4 | B7: 4 | C7: Orders | D7: e | F7: 5 | G7: 6 | H7: Inferred company | I7: 256 | K7: 0.001 | M7: 789 | N7: =M7*K7 -> 0.789
A8: 5 | B8: 7 | C8: Orders | D8: f | E8: 6 | G8: 7 | H8: Through Contact & Company | I8: 24 | K8: 0.001 | M8: 5 | N8: =M8*K8 -> 0.005
A9: 8 | B9: 8 | C9: Orders | D9: g | F9: 8 | G9: 8 | H9: Direct Through Order | I9: 51 | K9: 0.001 | M9: 1000000 | N9: =M9*K9 -> 1000

Sheet Object Relationships Diagram

Sheet Aggregations and Calculations
A1: Name | B1: Dashboards | C1: Description | D1: Dependancies
A2: Total Conversions | C2: Count of desired actions (purchases, sign-ups, etc.).
A3: Conversion Rate | C3: (Conversions / Audience Size) × 100
A4: Time to Conversion | C4: Avg. days between first marketing touchpoint and conversion.
A5: Conversion Rate by Channel | C5: Conversions per channel / Total audience reached via that channel.
A6: Churn Rate | C6: (Customers Lost / Total Customers at Start of Period) × 100
A7: Marketing Impact on Churn | C7: Reduction in churn among customers exposed to marketing.
A8: Attributed Marketing Impact -
A9: Attributed Revenue per Channel | C9: Revenue from customers exposed to marketing per channel.
A10: Incremental Lift from Marketing | C10: (Conversion Rate of Exposed Group - Conversion Rate of Non-Exposed Group)
A11: Marketing Influence Score | C11: Weighted impact of different marketing touchpoints on final outcomes.
A12: Multi-Touch Attribution Value per Path | C12: Total attributed revenue divided by the % of conversions that followed a specific marketing sequence.
A13: Customer Segmentation & Behavioural Trends -
A14: Customer Lifetime Value (CLV) Banding | C14: Avg. revenue per customer over a defined period.
A15: Retention Rate by Audience Segment | C15: % of customers retained within each segment (e.g., industry, location, tenure).
A16: Most Common Engagement Paths | C16: Rank sequences of interactions that most often lead to conversion.
A17: Content Effectiveness Score | C17: Engagement rate per marketing asset (emails, ads, videos, etc.).
E18: Business Description | F18: Technical Description
A19: Outcome Timeframe | B19: All Outcomes, Product Outcomes, Audience Analysis | C19: This is the Time that the outcome is recognised by the business. Here we are interested in the Raised date for orders, For other outcomes which field to use will vary | E19: “This is the time that the outcome is recognized by the business. Here we are interested in the Raised date for orders. For other outcomes, which date field to use can vary.” | F19: Typically derived from the “raised date” (or similar) in the orders/outcomes data. Stored in a field like outcome_date or order_raised_date. Used as a filter on dashboards to constrain the timeframe of recognized outcomes.
A20: Business Segment | B20: All Outcomes, Product Outcomes, Audience Analysis, Marketing Impact, Channel Impact | C20: SMB, CPS | E20: “SMB, CPS” | F20: A categorical/lookup field indicating the segment classification for each account or lead (e.g., 'SMB', 'CPS'). Likely stored in a field like business_segment in your master account/customer table.
A21: Total Conversions | B21: ??? | C21: The Number of Accounts with Orders by the number of distinct accounts in the Audience. | D21: Orders, Distinct Accounts, Audience | E21: “The Number of Accounts with Orders by the number of distinct Accounts in the Audience.” | F21: A count of unique accounts that have placed an order divided by the total number of distinct accounts in the relevant audience. E.g., COUNT(DISTINCT account_id WHERE has_order=true) / COUNT(DISTINCT account_id). Often displayed as a raw count (“converted accounts”) or a rate (“conversion rate”).
A22: Total Outcome Order Value | B22: All Outcomes, Product Outcomes, Specific Company Analysis, Audience Analysis | C22: Sum of Total_SOV for all raised Orders | E22: “Sum of Total_SOV for all raised Orders.” | F22: Aggregates the sum of value across all orders in a given timeframe or segment. E.g., SUM(order_total_sov) from orders (filtered by timeframe).
A23: Total Outcome Customer Value Change | B23: All Outcomes, Product Outcomes, Specific Company Analysis, Audience Analysis | C23: Option 1: Value Change = Total_SOV - PREV_TOTAL_SOV Keep this for only new Renewal or changed orders. This is for the date that the new order is raised. Option 2: Value Change = Sum (Total_SOV) Where Raised date in Timeframe - Sum (Total_SOV) Where Ceased Date in Timeframe Relies on Ceased dates being correct, Also need to consider how raised but ultimately failed orders are considered. | E23: “(Option 1) Value Change = Total_SOV - PREV_TOTAL_SOV. (Option 2) Value Change = Sum(Total_SOV) where raised date in timeframe - Sum(Total_SOV) where ceased date in timeframe.” | F23: Tracks how a customer’s total service/order value changes over time (new vs. ceased). One approach is current_sov - previous_sov. Alternatively, measure new SOV raised minus SOV ceased in the timeframe. Store or compute from orders data (raised_date, ceased_date).
A24: Total Outcome Churn | B24: All Outcomes, Product Outcomes, Specific Company Analysis, Audience Analysis | C24: Churn could be at 3 levels Customer, Product Group, Specific Product. Specific Product Option 1: For a Customer (Billing Account Level) A churn on a date occurs when on the previous day there was at least on active product for that customer. But on the selected day there are no longer any active products for the particular product specified. Products that cease but there exists another product that is linked as a renewal even if its a different product. Would not count as a product level churn. Product Family As Above but here looking at all product for a customer within a product family, If the count of live products for a product family for a customer goes from 1>0 This is a churn event for this customer (BAN). Again exclude from this products where there is a linked renewal for a product even if in a different family. Customer For a customer (BAN) a Churn occurs on a date where the count of live products goes from 1>0. Outstanding Questions: - Which is the field for the ceased date | E24: “Churn could be at 3 levels: Customer, Product Group, Specific Product. A churn event occurs on a date if the count of live products goes from 1→0 with no renewal link.” | F24: You can measure churn events/amount by comparing active product records day-to-day. E.g., a product is “ceased” on date X if it was active the prior day. Product-level or family-level churn excludes renewals. Technically, you might store churn_date or compare active_product_count from t to t-1.
A25: Attributed Outcome Order Value Amount | B25: All Outcomes, Product Outcomes, Specific Company Analysis, Audience Analysis, Marketing Impact, Channel Impact, Campaign Impact, Marketing Technology Impact | C25: Sum (Total_SOV for raised orders * Attribute %) Apply the attributed Percentage reduction to each raised order then Sum these. | E25: “Sum (Total_SOV for raised orders * Attribute %). Apply the attributed percentage to each raised order, then sum.” | F25: For each order, multiply its order_value (Total_SOV) by the marketing attribution factor (e.g., 0.3 if 30% is attributed to marketing). Then sum across all orders in the timeframe or segment. Technically: SUM(order_value * marketing_attribution_pct).
A26: Attributed Outcome Order Value Percentage | B26: All Outcomes, Product Outcomes, Specific Company Analysis, Audience Analysis, Marketing Impact, Channel Impact, Campaign Impact, Marketing Technology Impact | C26: Aggregated (Attributed Outcome order values amount) / Agreegated (Outcome order value amount) This is likely to be different to the sum of the attributed percentages. As it might be that larger orders have a larger marketing attribution and so the total amount attributed to marketing is higher once order values are taken into account. Here the order value could be any of SOV, SOV_GM, ICV, ICV_GM. Suggest the dashboard has some sort of switcher to move between these. | E26: (Percentage of total order value that is attributed to marketing.) | F26: Calculated as (Attributed Outcome Order Value Amount / Total Outcome Order Value) * 100. For a given dimension or grouping, you might do: SUM(order_value * attribution_pct) / SUM(order_value) * 100.
A27: Attributed Outcome Customer Value Change £ | B27: All Outcomes, Product Outcomes, Specific Company Analysis, Audience Analysis, Marketing Impact, Channel Impact, Campaign Impact, Marketing Technology Impact | E27: (Similar to “Customer Value Change,” but restricted to the fraction attributed to marketing.) | F27: For each relevant account or order, take the “value change” and multiply by the attribution factor. E.g., SUM( (new_sov - old_sov) * marketing_attribution_pct ) for the relevant set of records.
A28: Attributed Outcome Customer Value Change Percentage | B28: All Outcomes, Product Outcomes, Specific Company Analysis, Audience Analysis, Marketing Impact, Channel Impact, Campaign Impact, Marketing Technology Impact | E28: (Ratio of marketing-attributed customer value change to total customer value change.) | F28: (Attributed Outcome Customer Value Change £ / Total Outcome Customer Value Change) * 100.
A29: Attributed Outcome Churn | B29: All Outcomes, Product Outcomes, Specific Company Analysis, Audience Analysis, Marketing Impact, Channel Impact, Campaign Impact, Marketing Technology Impact | E29: “Churn could be at 3 levels… and we apply marketing attribution factor (or logic) to see which portion is attributed to marketing.” | F29: If marketing is credited with preventing or partially causing churn, you might track the fraction of churn events or churn amounts “tied” to marketing. The exact logic depends on your attribution model—e.g., if marketing prevented churn, or if a missed marketing touch contributed to churn. This is more specialized and may or may not appear on the Channel/Campaign dashboards unless explicitly needed.
A30: Attributed Outcome Churn Percentage | B30: All Outcomes, Product Outcomes, Specific Company Analysis, Audience Analysis, Marketing Impact, Channel Impact, Campaign Impact, Marketing Technology Impact | E30: (Percentage of total churn that was attributed to marketing, or possibly the share that was prevented by marketing.) | F30: Computed similarly to “Attributed Outcome Churn,” but expressed as a percentage: (Attributed Churn / Total Churn) * 100, or “churn avoided.” Not explicitly listed in Channel/Campaign/Tech dashboards in the PPT, so typically remains in the “outcomes” or “audience” views.
A31: Marketing Activity Channel group | B31: All Outcomes, Product Outcomes, Specific Company Analysis, Audience Analysis, Marketing Impact, Channel Impact, Campaign Impact, Marketing Technology Impact | C31: Web, Social, Outbound Comms | E31: “Web, Social, Outbound Comms,” etc. | F31: A high-level grouping of channels used for marketing. Often stored in a dimension table or a field like channel_group (e.g., 'web', 'social', 'outbound'). Widely used across multiple dashboards as a dimension or filter.
A32: Marketing Activity Channel | B32: Product Outcomes, Marketing Impact, Channel Impact, Campaign Impact, Marketing Technology Impact | E32: (A more granular channel—e.g., Email, Paid Search, LinkedIn Ads, etc.) | F32: A detailed channel field in your campaign/activity logs, e.g., marketing_channel = 'email'. In your dashboards, you might roll this up into “channel group.”
A33: Outcome Product Family | B33: All Outcomes, Product Outcomes,Channel Impact | E33: (Groups outcome products into families—e.g., Mobile, Broadband, Security, etc.) | F33: A categorical or lookup field that classifies products. Typically in a product dimension table: product_family_id → 'Mobile', 'Hosting', 'Security', etc. Seen in multiple “outcome-focused” dashboards and also in Channel Impact (the PPT specifically references “Product Families” as a dimension).
A34: Outcome Product | B34: Product Outcomes, Specific Company Analysis, Channel Impact, Campaign Impact | E34: (The specific product sold, renewed, or churned.) | F34: Typically references the exact product in the outcome. E.g., a field outcome_product_id or order_product_code. Displayed in product-level dashboards, or in the “outcome products” dimension for Channel/Campaign Impact.
A35: Campaign Product Family | B35: Marketing Impact, Channel Impact | E35: (Indicates which product family the campaign is targeting or associated with—e.g., a “Mobile” campaign.) | F35: A lookup from the campaign record to the targeted product family. E.g., campaign_target_product_family_id → 'Mobile'. Explicitly in Marketing Impact and Channel Impact; can also be relevant in Campaign Impact or Tech Impact if you want to see the product families each campaign aims at.
A36: Transactions Channel | B36: All Outcomes, Product Outcomes | C36: How did they transact the order | E36: “How did they transact the order?” (online, phone, in-person, etc.) | F36: A field in the order data indicating the fulfillment/purchase channel. Often called something like transaction_channel. The PPT references “transactions channel” especially in outcome-focused dashboards.
A37: Outcome Type | B37: All Outcomes, Product Outcomes | C37: Acquisition, Resign, Cross-Sell | E37: “Acquisition, Resign, Cross-Sell.” | F37: A categorical field describing the type of outcome event. E.g., 'acquisition', 'resign', 'cross_sell'. Typically stored in outcome_type.
A38: Outcome Intentionality - Product | B38: All Outcomes, Product Outcomes | C38: *Did outcome product match marketing target product | E38: “Did the outcome product match the marketing target product?” | F38: A boolean or categorical field indicating if the actual product purchased (outcome) aligns with the intended product from the campaign. E.g.: outcome_product_id == campaign_target_product_id.
A39: Outcome Intentionality - Outcome Type | B39: All Outcomes, Product Outcomes | E39: (Checks if the type of outcome matched the intended outcome type—e.g., an Acquisition campaign yields an Acquisition outcome.) | F39: Another boolean or categorical field indicating if the outcome type (e.g., cross-sell) matches the campaign’s intended type. E.g.: IF campaign_objective = 'Cross-sell' AND outcome_type = 'cross_sell' THEN 'Intentional' ELSE 'Not Intentional'.
A40: Number of Campaigns | B40: Product Outcomes, Marketing Impact, Channel Impact, Marketing Technology Impact | E40: (A count of how many distinct campaigns were run or influenced the selected outcomes/timeframe.) | F40: Computed by counting distinct campaign_id across all relevant records. E.g.: COUNT(DISTINCT campaign_id). PPT explicitly mentions “# of campaigns run” in Product Outcomes, Marketing Impact, Channel Impact, and Marketing Technology dashboards.
A41: No. Campaigns | B41: Product Outcomes, Specific Company Analysis, Audience Analysis,Marketing Impact,Channel Impact,Campaign Impact, Marketing Technology Impact | E41: (The list of or reference to campaigns that ran or influenced a period, product, or account.) | F41: References a campaign dimension or table. Used widely across the PPT wherever we want to display or filter by the campaigns that influenced an outcome. E.g., might store them as campaign_id in your activity logs.
A42: No. Marketing Assets | B42: Product Outcomes, Specific Company Analysis, Audience Analysis,Channel Impact, Campaign Impact, Marketing Technology Impact | C42: This is a count of the different marketing assets that have been used as part of this campaign. Distinct count on Asset ID. | E42: (List or dimension of marketing assets used: emails, ads, landing pages, etc.) | F42: A sub-dimension or child of a campaign. Typically stored as asset_id or references to creative items in the marketing platform. Multiple dashboards (Channel, Campaign, Tech Impact) mention “assets used” as a dimension or KPI.
A43: Audience Size - Companies | B43: Audience Analysis, Channel Impact | C43: Distinct count of the company IDs We might need a switcher here to move between different company ID references. Or it might be that the audience dictates which is the correct ID to use in this instance. | E43: (Number of companies in the audience.) | F43: Often COUNT(DISTINCT company_id) for the relevant “audience” definition.
A44: Audience Size - Individuals | B44: Specific Company Analysis, Audience Analysis, Channel Impact | C44: Distinct count of person ID | E44: (Number of individual contacts in the audience.) | F44: Often COUNT(DISTINCT person_id) or lead_id.
A45: Reached - Individuals | B45: Marketing Impact, Channel Impact, Campaign Impact, Marketing Technology Impact | C45: Distinct count of Persons ID's Where the person was Reached. Reached: For push marketing activities to a known audience. This is a marketing activity that has a status that is delivered or equivilent. For those we can count the distinct Person ID's For a pull activity this is the sum of the reached audience for that activity, This would be provided by the source system. i.e. Ad reach. | E45: (Number of individual contacts who actually received or engaged with marketing content.) | F45: Typically COUNT(DISTINCT person_id) who had a recorded marketing touch (e.g., email sent, ad impression, event registration). The PPT explicitly calls out “audience reached (companies/individuals)” in these four dashboards.
A46: Reached - Companies | B46: Marketing Impact, Channel Impact, Campaign Impact, Marketing Technology Impact | E46: (Number of companies that actually received/engaged with marketing.) | F46: Same as above, but at the company level: COUNT(DISTINCT company_id) that had at least one marketing touch.
A47: % Audience Reached - Companies | B47: Specific Company Analysis, Audience Analysis | E47: (Percentage of the total company audience that was reached.) | F47: (Audience Reached - Companies / Total Audience Companies) * 100.
A48: % Audience Reached - Individuals | B48: Specific Company Analysis, Audience Analysis | E48: (Percentage of the total individual audience that was reached.) | F48: (Audience Reached - Individuals / Total Audience Individuals) * 100.
A49: Engaged Companies | B49: Marketing Impact | E49: (Number of companies that actively engaged—clicked, responded, etc.) | F49: Typically COUNT(DISTINCT company_id) with a recorded engagement activity. Derived from logs of email clicks, form fills, event registrations, etc. The PPT mentions “engaged companies” in these four dashboards’ KPIs.
A50: Engaged Individuals | B50: Marketing Impact | E50: (Number of individual contacts that engaged.) | F50: Same as above, but at the person level: COUNT(DISTINCT person_id) with an engagement activity.
A51: Campaign Spend (Attributed) - Actual | B51: Specific Company Analysis, Audience Analysis, Marketing Impact,Channel Impact, Campaign Impact, Marketing Technology Impact | E51: (Amount of actual spend attributed to a particular outcome, segment, or account.) | F51: Typically from your marketing spend system, then allocated by an attribution percentage if needed: campaign_actual_spend * marketing_attribution_pct. Many PPT dashboards mention “campaign spend (actual/anticipated).”
A52: Campaign Spend (Attributed) - Planned | B52: Specific Company Analysis, Audience Analysis, Marketing Impact,Channel Impact, Campaign Impact, Marketing Technology Impact | E52: (Planned or budgeted campaign spend, likewise attributed.) | F52: Similar to the above but uses planned spend data, e.g. campaign_planned_spend * marketing_attribution_pct.
A53: Individuals | B53: Specific Company Analysis | E53: (List of individuals/contacts for a given company.) | F53: In that dashboard, you often want to see which specific people in the account had marketing touches or outcomes. Could be a table of person_id, name, or a count.
A54: Marketing Engagement Levels | B54: Audience Analysis | C54: This is grouping the overall engagement of individuals into cohorts. No Engagement - never any recorded engagement against this individual Minor Historic Engagement - Low levels of Interactions but non in the last 6 months. (1 -2 per 6 months) Minor Recent Engagement - Low Levels of Interactions within the last 6 months. (1-2 in last 6 months) Major Recent Engagement - Multiple meaningful interactions within the last 6 months Alternatively once we have a scoring model in place then we can cohort based on the score of an individual. | E54: “Groups overall engagement of individuals into cohorts (No Engagement, Minor, Major, etc.). Could also be based on a scoring model.” | F54: A categorical or score-based field that classifies an individual’s engagement. For example, logic like: IF last_6mo_interactions ≥ 3 THEN "Major Recent Engagement" ELSE…. Typically computed from marketing activity logs.
A55: Historic Customer Value | B55: Audience Analysis | C55: Only Relevant at the account level. This is the Sum total of all Total_SOV. | E55: “Only relevant at the account level. This is the sum total of all Total_SOV.” | F55: A summation of total historical SOV for an account, stored or calculated as historic_sov.
A56: Customer Tenure | B56: Audience Analysis | E56: (How long the customer has been with BT—e.g., months or years.) | F56: Could be (current_date - customer_start_date) or a banded classification: '0-6 months', '6-12 months', '12+ months'. Typically stored in the account record or derived on the fly.
A57: Marketing Activity Date | B57: Specific Company Analysis, Audience Analysis, Marketing Impact,Channel Impact, Campaign Impact, Marketing Technology Impact | E57: (Date on which a particular marketing activity occurred—e.g., email send date, ad launch date, etc.) | F57: A field in the marketing activity logs, e.g., activity_date. The PPT specifically notes “Marketing Activity Date” as a filter for these dashboards.
A58: Marketing Technology | B58: Specific Company Analysis, Audience Analysis, Marketing Impact,Channel Impact, Campaign Impact, Marketing Technology Impact | E58: (Indicates which platform or tool was used, e.g., Marketo, Eloqua, Pardot, etc.) | F58: A categorical field referencing the marketing technology. E.g., marketing_tech_id → 'Marketo'. The PPT explicitly references it for Marketing Impact (to show which tech was used) and Marketing Technology Impact (the main focus).
A59: Campaign Objective | B59: Marketing Impact, Channel Impact, Campaign Impact, Marketing Technology Impact | E59: “Welcome, Acquisition, Upsell, Cross-sell, Retention, In-Life, Service, Migration, Out of Contract.” | F59: A categorical field describing the main goal of the campaign. E.g., campaign_objective = 'Retention'. All these dashboards can break down or filter by the objective.
A60: Audience Vertical | B60: Audience Analysis, Marketing Impact,Channel Impact, Campaign Impact, Marketing Technology Impact | E60: (Industry vertical or market segment, e.g. 'Finance', 'Retail', 'Education', etc.) | F60: A lookup to an industry/vertical classification. Possibly stored as audience_vertical. The PPT specifically names “Industry & Vertical” for Audience Analysis, and also “Audience Groupings” for Marketing Impact, so it can appear in other dashboards if you want a breakdown by vertical.
A61: Audience Industry | B61: Audience Analysis, Marketing Impact,Channel Impact, Campaign Impact, Marketing Technology Impact | E61: (Another layer of audience classification, e.g. 'Financial Services', 'Healthcare', etc.) | F61: Similar to “Audience Vertical.” Could be a separate or more detailed field, e.g., audience_industry_code.
A62: Audience Company Size | B62: Audience Analysis, Marketing Impact,Channel Impact, Campaign Impact, Marketing Technology Impact | E62: (Breakdown by number of employees, revenue band, etc.) | F62: A categorical or numeric field for company size. E.g. '1-50 employees', '51-200', etc. Possibly stored as company_size_band. Many dashboards mention “Audience Groupings” that can include company size.

Sheet Channels
A1: channel_id | B1: channel_name | C1: channel_group | D1: Identifiable method | E1: type | F1: Comment | G1: communication_mode | H1: Interaction Types | I1: POC | J1: Interaction Data Source | K1: GCP Data Availability
B2: Paid Digital Ads | C2: ATL | D2: IP Inferred | E2: Digital | G2: Pull | H2: =_xlfn.XLOOKUP(B2,Table2[Channel Name],Table2[Interactions Concatenated],"",0,1) -> Viewed;Clicked;Submit Form | J2: EssenceMediacom | K2: Data source unknown
B3: Content Syndication | C3: ATL | D3: Audience Inferred | E3: Digital | G3: Pull | H3: =_xlfn.XLOOKUP(B3,Table2[Channel Name],Table2[Interactions Concatenated],"",0,1) -> Viewed;Clicked;Submit Form
B4: Web | C4: ATL | D4: IP Inferred or Better | E4: Digital | G4: Pull | H4: =_xlfn.XLOOKUP(B4,Table2[Channel Name],Table2[Interactions Concatenated],"",0,1) -> Page View;Link Click;Submit Form;Watch Video;Download;Live Chat? | J4: Adobe web/app visits | K4: Data sources are knows, exists partially in CCN
B5: Above the Line - Non Digital | C5: ATL | D5: Audience Inferred | E5: Physical | F5: Placeholder For multiple channels | G5: Pull | H5: =_xlfn.XLOOKUP(B5,Table2[Channel Name],Table2[Interactions Concatenated],"",0,1) -> Viewed
B6: Social Posts | C6: ATL | D6: Audience Inferred | E6: Digital | G6: Pull | H6: =_xlfn.XLOOKUP(B6,Table2[Channel Name],Table2[Interactions Concatenated],"",0,1) -> Viewed;Clicked;Responded
B7: Social Outbound Messages | C7: BTL | D7: Known Person | E7: Digital | G7: Push | H7: =_xlfn.XLOOKUP(B7,Table2[Channel Name],Table2[Interactions Concatenated],"",0,1) -> Viewed;Clicked;Responded;Opt-Out
B8: Virtual Events | C8: BTL | D8: Self Identified | E8: Events | G8: Push | H8: =_xlfn.XLOOKUP(B8,Table2[Channel Name],Table2[Interactions Concatenated],"",0,1) -> Registered;Attended;View on Demand
B9: F2F Events | C9: BTL | D9: Self Identified | E9: Events | G9: Push | H9: =_xlfn.XLOOKUP(B9,Table2[Channel Name],Table2[Interactions Concatenated],"",0,1) -> Registered;Attended
B10: Webinars | C10: BTL | D10: Self Identified | E10: Events | H10: =_xlfn.XLOOKUP(B10,Table2[Channel Name],Table2[Interactions Concatenated],"",0,1) -> Registered;Attended;View on Demand
B11: Direct Mail | C11: BTL | D11: Known Person | E11: Physical | H11: =_xlfn.XLOOKUP(B11,Table2[Channel Name],Table2[Interactions Concatenated],"",0,1) -> Sent;Received;Bounced | I11: TRUE
B12: Whatsapp | C12: BTL | D12: Known Person | E12: Digital | H12: =_xlfn.XLOOKUP(B12,Table2[Channel Name],Table2[Interactions Concatenated],"",0,1) -> Sent;Received;Read;Clicked;Responded;Opt-Out
B13: RCS | C13: BTL | D13: Known Person | E13: Digital | H13: =_xlfn.XLOOKUP(B13,Table2[Channel Name],Table2[Interactions Concatenated],"",0,1) -> Sent;Received;Read;Clicked;Responded;Opt-Out;Opened
B14: Email | C14: BTL | D14: Known Person | E14: Digital | H14: =_xlfn.XLOOKUP(B14,Table2[Channel Name],Table2[Interactions Concatenated],"",0,1) -> Sent;Received;Bounced;Opened;Clicked;Opt-Out;Responded | I14: TRUE | J14: Marketo email activities | K14: Data sources are known, exists in GCP CCN
B15: SMS | C15: BTL | D15: Known Person | E15: Digital | H15: =_xlfn.XLOOKUP(B15,Table2[Channel Name],Table2[Interactions Concatenated],"",0,1) -> Sent;Received;Bounced;Clicked;Responsed;Opt-Out | I15: TRUE | J15: IMI | K15: Data does not exist in GCP
B16: MMS | C16: BTL | D16: Known Person | E16: Digital | H16: =_xlfn.XLOOKUP(B16,Table2[Channel Name],Table2[Interactions Concatenated],"",0,1) -> Sent;Received;Bounced;Clicked;Responsed;Opt-Out
B17: App Push Notification | C17: BTL | D17: Known Person | E17: Digital | H17: =_xlfn.XLOOKUP(B17,Table2[Channel Name],Table2[Interactions Concatenated],"",0,1) -> Sent;Received;Clicked
B18: Telemarketing | C18: BTL | D18: Known Person | E18: Conversation | H18: =_xlfn.XLOOKUP(B18,Table2[Channel Name],Table2[Interactions Concatenated],"",0,1) -> Attempted;Answered;Conversed | J18: NRT | K18: Data sources are known, exists in GCP CCN
B19: Online Chat | C19: BTL | D19: Self Identified / IP Inferred | E19: Conversation | H19: =_xlfn.XLOOKUP(B19,Table2[Channel Name],Table2[Interactions Concatenated],"",0,1) -> Initiated;Answered;Disconnected | J19: NRT | K19: Data sources are known, exists in GCP CCN
B20: Salesperson Meetings | C20: Sales | D20: Known Person | E20: Conversation | H20: =_xlfn.XLOOKUP(B20,Table2[Channel Name],Table2[Interactions Concatenated],"",0,1) -> Invited;Attended
B21: Salesperson Calls | C21: Sales | D21: Known Person | E21: Conversation | H21: =_xlfn.XLOOKUP(B21,Table2[Channel Name],Table2[Interactions Concatenated],"",0,1) -> Dialled;Answered;Engaged
B22: Salesperson Email | C22: Sales | D22: Known Person | E22: Digital | H22: =_xlfn.XLOOKUP(B22,Table2[Channel Name],Table2[Interactions Concatenated],"",0,1) -> Sent;Received;Bounced;Opened;Clicked;Opt-Out;Responded
B23: Inbound Calls | C23: BTL | D23: Known Person | E23: Conversation | G23: Pull | H23: =_xlfn.XLOOKUP(B23,Table2[Channel Name],Table2[Interactions Concatenated],"",0,1) -> Called;Not Answered | J23: NRT | K23: Data sources are known, exists in GCP CCN

Sheet Interaction Types
A1: Channel Name | B1: Interactions Concatenated | C1: Interactions | D1: Column1 | E1: Column2 | F1: Column3 | G1: Column4 | H1: Column5 | I1: Column6
A2: Above the Line - Non Digital | B2: =_xlfn.TEXTJOIN(";",TRUE,C2:I2) -> Viewed | C2: Viewed
A3: App Push Notification | B3: =_xlfn.TEXTJOIN(";",TRUE,C3:I3) -> Sent;Received;Clicked | C3: Sent | D3: Received | F3: Clicked
A4: Content Syndication | B4: =_xlfn.TEXTJOIN(";",TRUE,C4:I4) -> Viewed;Clicked;Submit Form | C4: Viewed | D4: Clicked | E4: Submit Form
A5: Direct Mail | B5: =_xlfn.TEXTJOIN(";",TRUE,C5:I5) -> Sent;Received;Bounced | C5: Sent | D5: Received | E5: Bounced
A6: Email | B6: =_xlfn.TEXTJOIN(";",TRUE,C6:I6) -> Sent;Received;Bounced;Opened;Clicked;Opt-Out;Responded | C6: Sent | D6: Received | E6: Bounced | F6: Opened | G6: Clicked | H6: Opt-Out | I6: Responded
A7: F2F Events | B7: =_xlfn.TEXTJOIN(";",TRUE,C7:I7) -> Registered;Attended | C7: Registered | D7: Attended
A8: Inbound Calls | B8: =_xlfn.TEXTJOIN(";",TRUE,C8:I8) -> Called;Not Answered | C8: Called | D8: Not Answered
A9: MMS | B9: =_xlfn.TEXTJOIN(";",TRUE,C9:I9) -> Sent;Received;Bounced;Clicked;Responsed;Opt-Out | C9: Sent | D9: Received | E9: Bounced | F9: Clicked | G9: Responsed | H9: Opt-Out
A10: Online Chat | B10: =_xlfn.TEXTJOIN(";",TRUE,C10:I10) -> Initiated;Answered;Disconnected | C10: Initiated | D10: Answered | E10: Disconnected
A11: Paid Digital Ads | B11: =_xlfn.TEXTJOIN(";",TRUE,C11:I11) -> Viewed;Clicked;Submit Form | C11: Viewed | D11: Clicked | E11: Submit Form
A12: RCS | B12: =_xlfn.TEXTJOIN(";",TRUE,C12:I12) -> Sent;Received;Read;Clicked;Responded;Opt-Out;Opened | C12: Sent | D12: Received | E12: Read | F12: Clicked | G12: Responded | H12: Opt-Out | I12: Opened
A13: Salesperson Calls | B13: =_xlfn.TEXTJOIN(";",TRUE,C13:I13) -> Dialled;Answered;Engaged | C13: Dialled | D13: Answered | E13: Engaged
A14: Salesperson Email | B14: =_xlfn.TEXTJOIN(";",TRUE,C14:I14) -> Sent;Received;Bounced;Opened;Clicked;Opt-Out;Responded | C14: Sent | D14: Received | E14: Bounced | F14: Opened | G14: Clicked | H14: Opt-Out | I14: Responded
A15: Salesperson Meetings | B15: =_xlfn.TEXTJOIN(";",TRUE,C15:I15) -> Invited;Attended | C15: Invited | D15: Attended
A16: SMS | B16: =_xlfn.TEXTJOIN(";",TRUE,C16:I16) -> Sent;Received;Bounced;Clicked;Responsed;Opt-Out | C16: Sent | D16: Received | E16: Bounced | F16: Clicked | G16: Responsed | H16: Opt-Out
A17: Social Outbound Messages | B17: =_xlfn.TEXTJOIN(";",TRUE,C17:I17) -> Viewed;Clicked;Responded;Opt-Out | C17: Viewed | D17: Clicked | E17: Responded | F17: Opt-Out
A18: Social Posts | B18: =_xlfn.TEXTJOIN(";",TRUE,C18:I18) -> Viewed;Clicked;Responded | C18: Viewed | D18: Clicked | E18: Responded
A19: Telemarketing | B19: =_xlfn.TEXTJOIN(";",TRUE,C19:I19) -> Attempted;Answered;Conversed | C19: Attempted | D19: Answered | E19: Conversed
A20: Virtual Events | B20: =_xlfn.TEXTJOIN(";",TRUE,C20:I20) -> Registered;Attended;View on Demand | C20: Registered | D20: Attended | E20: View on Demand
A21: Web | B21: =_xlfn.TEXTJOIN(";",TRUE,C21:I21) -> Page View;Link Click;Submit Form;Watch Video;Download;Live Chat? | C21: Page View | D21: Link Click | E21: Submit Form | F21: Watch Video | G21: Download | H21: Live Chat?
A22: Webinars | B22: =_xlfn.TEXTJOIN(";",TRUE,C22:I22) -> Registered;Attended;View on Demand | C22: Registered | D22: Attended | E22: View on Demand
A23: Whatsapp | B23: =_xlfn.TEXTJOIN(";",TRUE,C23:I23) -> Sent;Received;Read;Clicked;Responded;Opt-Out | C23: Sent | D23: Received | E23: Read | F23: Clicked | G23: Responded | H23: Opt-Out
